liver_ct_segmentation_package/__init__.py
liver_ct_segmentation_package/cli_feat_imp_ggcam.py
liver_ct_segmentation_package/cli_model_dl.py
liver_ct_segmentation_package/cli_pred.py
liver_ct_segmentation_package/cli_uncert_pred.py
liver_ct_segmentation_package/data/img_117.mrc
liver_ct_segmentation_package/data/lab_117.mrc
liver_ct_segmentation_package/data_loading/__init__.py
liver_ct_segmentation_package/data_loading/data_loader.py
liver_ct_segmentation_package/losses/__init__.py
liver_ct_segmentation_package/losses/focal_loss.py
liver_ct_segmentation_package/metrics/__init__.py
liver_ct_segmentation_package/metrics/metrics.py
liver_ct_segmentation_package/model/__init__.py
liver_ct_segmentation_package/model/model.py
liver_ct_segmentation_package/model/unet_3d_models.py
liver_ct_segmentation_package/utils/__init__.py
liver_ct_segmentation_package/utils/uncertainty.py
liver_ct_segmentation_package/utils/utils.py
liver_ct_segmentation_package/utils/volume_utils.py
liver_ct_segmentation_package-1.6.0.dist-info/LICENSE
liver_ct_segmentation_package-1.6.0.dist-info/METADATA
liver_ct_segmentation_package-1.6.0.dist-info/WHEEL
liver_ct_segmentation_package-1.6.0.dist-info/entry_points.txt
liver_ct_segmentation_package-1.6.0.dist-info/top_level.txt
liver_ct_segmentation_package-1.6.0.dist-info/RECORD
