Metadata-Version: 2.1
Name: liver-ct-segmentation-package
Version: 1.6.0
Summary: Prediction package for U-Net models trained on the LiTS dataset.
Home-page: https://github.com/luiskuhn/liver-ct-segmentation-package
Author: Luis Kuhn Cuellar
Author-email: luis.kuhn@gmail.com
License: MIT
Keywords: liver-ct-segmentation-package
Platform: UNKNOWN
Classifier: Development Status :: 2 - Pre-Alpha
Classifier: Intended Audience :: Developers
Classifier: License :: OSI Approved :: MIT License
Classifier: Natural Language :: English
Classifier: Programming Language :: Python :: 3
Classifier: Programming Language :: Python :: 3.7
Classifier: Programming Language :: Python :: 3.8
Classifier: Programming Language :: Python :: 3.9
Requires-Python: >=3.7
Requires-Dist: rich (==9.10.0)
Requires-Dist: torch (==1.7.1)
Requires-Dist: pytorch-lightning (==1.1.8)
Requires-Dist: mlflow (==1.13.1)
Requires-Dist: mrcfile (==1.3.0)
Requires-Dist: captum (==0.4.0)
